mitoo/__init__.py
mitoo/__main__.py
mitoo/adapters.py
mitoo/comparisons.py
mitoo/constants.py
mitoo/conversation.py
mitoo/filters.py
mitoo/mitoo.py
mitoo/parsing.py
mitoo/preprocessors.py
mitoo/response_selection.py
mitoo/trainers.py
mitoo/utils.py
mitoo/ext/__init__.py
mitoo/ext/sqlalchemy_app/__init__.py
mitoo/ext/sqlalchemy_app/models.py
mitoo/ext/sqlalchemy_app/types.py
mitoo/input/__init__.py
mitoo/input/input_adapter.py
mitoo/input/microsoft.py
mitoo/input/terminal.py
mitoo/input/variable_input_type_adapter.py
mitoo/logic/__init__.py
mitoo/logic/best_match.py
mitoo/logic/logic_adapter.py
mitoo/logic/low_confidence.py
mitoo/logic/mathematical_evaluation.py
mitoo/logic/multi_adapter.py
mitoo/logic/no_knowledge_adapter.py
mitoo/logic/specific_response.py
mitoo/logic/time_adapter.py
mitoo/output/__init__.py
mitoo/output/microsoft.py
mitoo/output/output_adapter.py
mitoo/output/terminal.py
mitoo/storage/__init__.py
mitoo/storage/django_storage.py
mitoo/storage/mongodb.py
mitoo/storage/sql_storage.py
mitoo/storage/storage_adapter.py
mitoo-1.9.9.dist-info/METADATA
mitoo-1.9.9.dist-info/RECORD
mitoo-1.9.9.dist-info/WHEEL
mitoo-1.9.9.dist-info/top_level.txt
