Metadata-Version: 2.1
Name: mitoo
Version: 1.9.9
Summary: Python based chatbot framework with voice output
Home-page: https://github.com/sobhanlenka/mitoo
Author: Sobhan Kumar Lenka
Author-email: sobhanlenka@gmail.com
License: UNKNOWN
Platform: UNKNOWN
Classifier: Programming Language :: Python :: 3
Classifier: License :: OSI Approved :: MIT License
Classifier: Operating System :: OS Independent
